odoo/addons/account_move_search_line/README.rst
odoo/addons/account_move_search_line/__init__.py
odoo/addons/account_move_search_line/__manifest__.py
odoo/addons/account_move_search_line/i18n/account_move_search_line.pot
odoo/addons/account_move_search_line/i18n/da.po
odoo/addons/account_move_search_line/readme/DESCRIPTION.rst
odoo/addons/account_move_search_line/static/description/icon.png
odoo/addons/account_move_search_line/static/description/index.html
odoo/addons/account_move_search_line/views/account_move_views.xml
odoo_addon_account_move_search_line-15.0.1.0.0.6.dist-info/METADATA
odoo_addon_account_move_search_line-15.0.1.0.0.6.dist-info/WHEEL
odoo_addon_account_move_search_line-15.0.1.0.0.6.dist-info/top_level.txt
odoo_addon_account_move_search_line-15.0.1.0.0.6.dist-info/RECORD
